[
    {
        "hash": 2947007567,
        "original": "Grand Easton Terminal",
        "translated": "Grand Easton车站",
        "desc": ""
    },
    {
        "hash": 2886589611,
        "original": "Easton, Algonquin",
        "translated": "Algonquin, Easton",
        "desc": ""
    },
    {
        "hash": 2001775558,
        "original": "Grand Easton Terminal, with its famous vaulted ceiling, is one of the busiest train stations in the world and is widely considered to be a wonder of Beaux-Arts architecture.  Buy a ticket, have a seat, and remember the freedom of decades past where you could smoke a cigarette or score some drugs in a train station bathroom and it wasn't on the friggin' evening news.",
        "translated": "Grand Easton车站以它的拱顶闻名，是全世界最繁忙的车站之一，也被认为是学院派建筑的奇迹。买张票，找个座，怀念一下几十年前在车站厕所里抽烟吸毒还不会被晚间新闻报道的年代吧。",
        "desc": ""
    }
]