[
    {
        "hash": 3120865626,
        "original": "Pupil: Dino Perdente",
        "translated": "姓名：Dino Perdente",
        "desc": ""
    },
    {
        "hash": 1593222556,
        "original": "Class of: 1997",
        "translated": "届别：1997届",
        "desc": ""
    },
    {
        "hash": 1840190494,
        "original": "High School: Alderney  City Tech",
        "translated": "学校：Alderney市技术学院",
        "desc": ""
    },
    {
        "hash": 3858296213,
        "original": "NICKNAME:",
        "translated": "",
        "desc": ""
    },
    {
        "hash": 2635767579,
        "original": "The Hoseman",
        "translated": "喷水员",
        "desc": ""
    },
    {
        "hash": 3079282705,
        "original": "BIO:",
        "translated": "",
        "desc": ""
    },
    {
        "hash": 2794038134,
        "original": "What's up losers???!!!! It's the Hoseman here! MVP 1997!!! You know it - yeah you do!! Working part-time at a gas station and full-time at chasing ass!!! Some things never change! I still live with my Mom in Alderney City and go out drinking with Fishface, Spunky and Bubble every night! SWEET! High school ring as well. I'd like to hear from any of the hot chicks I used to hook up with. Suzie, Marianne, Yolanda, Chu Hua... FIRE, FIRE!! Quick, where's the hose? Right here, baby, right here. Check me out. Fuckin A!",
        "translated": "屌丝们怎么样啊？？？！！！我是喷水员！1997届的最佳选手！！！你懂的，你肯定懂！！我兼职在加油站打工，全职追妹子！！！有些东西永远不会变！我还是和我妈一起住在Alderney市，每晚都和Fishface，Spunky和Bubble一起出去喝酒！真爽！高中时也是如此。我想收到曾经被我勾搭过的辣妹们的回复，Suzie、Marianne、Yolanda、Chu Hua... 太烧啦，着火啦！！快，消防龙头在哪？在我这，宝贝，就在这儿。来看看我吧。爽爆！",
        "desc": ""
    },
    {
        "hash": 3740797274,
        "original": "MESSAGE:",
        "translated": "",
        "desc": ""
    },
    {
        "hash": 1717614765,
        "original": "Hoseman - you rock!! Last night fucking RULED!",
        "translated": "喷水员，你太屌了！！昨天晚上真爽！",
        "desc": ""
    },
    {
        "hash": 3247262252,
        "original": "- Spunky",
        "translated": "",
        "desc": ""
    },
    {
        "hash": 3740797274,
        "original": "MESSAGE:",
        "translated": "",
        "desc": ""
    },
    {
        "hash": 930710004,
        "original": "For the record, Dino, you were the worst lay of my life. More like a straw than a hose.",
        "translated": "Dino，在此申明，你是我这辈子最烂的炮友。就是根吸管，哪是水管啊。",
        "desc": ""
    },
    {
        "hash": 1806705306,
        "original": "- Yolanda.",
        "translated": "",
        "desc": ""
    },
    {
        "hash": 2916731717,
        "original": "BACK TO MAIN PAGE",
        "translated": "",
        "desc": ""
    }
]